govuk_frontend_django/__init__.py
govuk_frontend_django/components/__init__.py
govuk_frontend_django/components/accordion.py
govuk_frontend_django/components/back_link.py
govuk_frontend_django/components/base.py
govuk_frontend_django/components/breadcrumbs.py
govuk_frontend_django/components/button.py
govuk_frontend_django/components/character_count.py
govuk_frontend_django/components/checkboxes.py
govuk_frontend_django/components/cookie_banner.py
govuk_frontend_django/components/date_input.py
govuk_frontend_django/components/details.py
govuk_frontend_django/components/error_message.py
govuk_frontend_django/components/error_summary.py
govuk_frontend_django/components/exit_this_page.py
govuk_frontend_django/components/fieldset.py
govuk_frontend_django/components/file_upload.py
govuk_frontend_django/components/footer.py
govuk_frontend_django/components/header.py
govuk_frontend_django/components/hint.py
govuk_frontend_django/components/input.py
govuk_frontend_django/components/inset_text.py
govuk_frontend_django/components/label.py
govuk_frontend_django/components/notification_banner.py
govuk_frontend_django/components/pagination.py
govuk_frontend_django/components/panel.py
govuk_frontend_django/components/password_input.py
govuk_frontend_django/components/phase_banner.py
govuk_frontend_django/components/radios.py
govuk_frontend_django/components/select.py
govuk_frontend_django/components/service_navigation.py
govuk_frontend_django/components/skip_link.py
govuk_frontend_django/components/summary_list.py
govuk_frontend_django/components/table.py
govuk_frontend_django/components/tabs.py
govuk_frontend_django/components/tag.py
govuk_frontend_django/components/task_list.py
govuk_frontend_django/components/textarea.py
govuk_frontend_django/components/warning_text.py
govuk_frontend_django/py.typed
govuk_frontend_django/templates/govuk_frontend_django/base.html
govuk_frontend_django/templatetags/__init__.py
govuk_frontend_django/templatetags/govuk_frontend_django/__init__.py
govuk_frontend_django-0.15.2.dist-info/LICENSE
govuk_frontend_django-0.15.2.dist-info/METADATA
govuk_frontend_django-0.15.2.dist-info/WHEEL
govuk_frontend_django-0.15.2.dist-info/RECORD
