Metadata-Version: 2.1
Name: govuk-frontend-django
Version: 0.15.2
Summary: Django functionality to help when building a GOV.UK website.
Home-page: https://uktrade.github.io/govuk-frontend-django/
License: MIT
Author: DBT Live Service Team
Author-email: live.services@digital.trade.gov.uk
Requires-Python: >=3.9,<4.0
Classifier: License :: OSI Approved :: MIT License
Classifier: Programming Language :: Python :: 3
Classifier: Programming Language :: Python :: 3.9
Classifier: Programming Language :: Python :: 3.10
Classifier: Programming Language :: Python :: 3.11
Classifier: Programming Language :: Python :: 3.12
Requires-Dist: Django (>=4.1.9,<6)
Requires-Dist: govuk-frontend-jinja (==3.5.0)
Requires-Dist: jinja2 (>=3.1.2,<4.0.0)
Project-URL: Documentation, https://uktrade.github.io/govuk-frontend-django/
Project-URL: Repository, https://github.com/uktrade/govuk-frontend-django/
